mL/KNN.py
mL/PCA.py
mL/SVM.py
mL/__init__.py
demo_test-1.0.dist-info/LICENSE
demo_test-1.0.dist-info/METADATA
demo_test-1.0.dist-info/WHEEL
demo_test-1.0.dist-info/top_level.txt
demo_test-1.0.dist-info/RECORD
