Metadata-Version: 2.1
Name: demo-test
Version: 1.0
Summary: first Pypi Project_test
Home-page: UNKNOWN
Author: Zhong-Ying
Author-email: m7536204@gmail.com
License: UNKNOWN
Keywords: pypi
Platform: UNKNOWN
